LICENSE
jupyter_paint_segment/__init__.py
jupyter_paint_segment/postprocess.py
jupyter_paint_segment/static/icons/brush.svg
jupyter_paint_segment/static/icons/eraser.svg
jupyter_paint_segment/static/icons/rectangle.svg
jupyter_paint_segment/static/index.html
jupyter_paint_segment/static/paint_widget.js
jupyter_paint_segment/static/styles.css
jupyter_paint_segment/types.py
jupyter_paint_segment/utils.py
jupyter_paint_segment/widget.py
jupyter_paint_segment-0.1.0.dist-info/LICENSE
jupyter_paint_segment-0.1.0.dist-info/METADATA
jupyter_paint_segment-0.1.0.dist-info/WHEEL
jupyter_paint_segment-0.1.0.dist-info/RECORD
