Metadata-Version: 2.1
Name: jupyter_paint_segment
Version: 0.1.0
Summary: A jupyter widget for manual image segmantation
Home-page: https://github.com/adusachev/jupyter-paint-segment
License: MIT
Keywords: jupyter,widget,segmentation,image
Author: adusachev
Author-email: adusachev@yandex.ru
Requires-Python: >=3.9
Classifier: Framework :: Jupyter
Classifier: Intended Audience :: Developers
Classifier: Intended Audience :: Science/Research
Classifier: License :: OSI Approved :: MIT License
Classifier: Programming Language :: Python
Classifier: Programming Language :: Python :: 3
Classifier: Programming Language :: Python :: 3.9
Classifier: Programming Language :: Python :: 3.10
Classifier: Programming Language :: Python :: 3.11
Classifier: Programming Language :: Python :: 3.12
Classifier: Programming Language :: Python :: 3.13
Requires-Dist: anywidget (>=0.9.15,<0.10.0)
Requires-Dist: matplotlib (>=3.7.5,<4.0.0)
Requires-Dist: opencv-python (>=4.11.0.86,<5.0.0.0)
Requires-Dist: pandas (>=2.0.3,<3.0.0)
Requires-Dist: pillow (>=10.4.0,<11.0.0)
Project-URL: Repository, https://github.com/adusachev/jupyter-paint-segment
